eva_vcf_merge/VERSION
eva_vcf_merge/__init__.py
eva_vcf_merge/detect.py
eva_vcf_merge/merge.py
eva_vcf_merge/multistage.py
eva_vcf_merge/utils.py
eva_vcf_merge-0.0.7.dist-info/LICENSE
eva_vcf_merge-0.0.7.dist-info/METADATA
eva_vcf_merge-0.0.7.dist-info/WHEEL
eva_vcf_merge-0.0.7.dist-info/top_level.txt
eva_vcf_merge-0.0.7.dist-info/RECORD
